README.md
setup.cfg
setup.py
anthill/common/__init__.py
anthill/common/access.py
anthill/common/admin.py
anthill/common/aqmp.py
anthill/common/cluster.py
anthill/common/database.py
anthill/common/deployment.py
anthill/common/discover.py
anthill/common/environment.py
anthill/common/events.py
anthill/common/gen.py
anthill/common/handler.py
anthill/common/internal.py
anthill/common/jsonrpc.py
anthill/common/keyvalue.py
anthill/common/login.py
anthill/common/model.py
anthill/common/monitoring.py
anthill/common/profile.py
anthill/common/pubsub.py
anthill/common/rabbitconn.py
anthill/common/rabbitrpc.py
anthill/common/ratelimit.py
anthill/common/schedule.py
anthill/common/server.py
anthill/common/sign.py
anthill/common/singleton.py
anthill/common/source.py
anthill/common/testing.py
anthill/common/validate.py
anthill/common/zeromq.py
anthill/common/options/__init__.py
anthill/common/options/default.py
anthill/common/social/__init__.py
anthill/common/social/facebook.py
anthill/common/social/google.py
anthill/common/social/mailru.py
anthill/common/social/steam.py
anthill/common/social/vk.py
anthill/common/social/xsolla.py
anthill/common/social/apis/__init__.py
anthill/common/tests/__init__.py
anthill/common/tests/test_profile.py
anthill_common.egg-info/PKG-INFO
anthill_common.egg-info/SOURCES.txt
anthill_common.egg-info/dependency_links.txt
anthill_common.egg-info/namespace_packages.txt
anthill_common.egg-info/not-zip-safe
anthill_common.egg-info/requires.txt
anthill_common.egg-info/top_level.txt