Metadata-Version: 1.0
Name: anthill-common
Version: 0.2.4
Summary: Common utils for Anthill Platform
Home-page: https://github.com/anthill-platform/anthill-common
Author: desertkun
Author-email: desertkun@gmail.com
License: MIT
Platform: UNKNOWN
